{
    "title": "2013-2014",
    "year":"2013-2014",
    "members":[
        {"name":"REV.VARGHESE GEORGE","address":"Parsonage","mobile":"","postion":"PRESIDENT","image":"/images/uploads/VARGHESE-GEORGE.jpeg"},
{"name":"GEORGE THOMAS","address":"NAITHALLOOR MANNIL","mobile":"9447114473","postion":"VICE PRESIDENT","image":"/images/uploads/blank-profile-picture.png"},
{"name":"SAJI T. MATHEW","address":"THANATH SHIGINE VILLA","mobile":"","postion":"TRUSTEE (FINANCE)","image":"/images/uploads/blank-profile-picture.png"},
{"name":"SAJU JOHN","address":"MENONPRAMBIL","mobile":"","postion":"TRUSTEE (ACCOUNTS)","image":"/images/uploads/blank-profile-picture.png"},
{"name":"M.C. ALEXANDER","address":"MAMMUTTIL","mobile":"9495112896","postion":"SECRETARY","image":"/images/uploads/blank-profile-picture.png"},
{"name":"P.M. MATHEW","address":"PAZHUR","mobile":"9605429633","postion":"LAY LEADER","image":"/images/uploads/blank-profile-picture.png"}
    ]
}